[
    {
        "_id": "65a72102ef7de121883fc232",
        "job": "Психолог",
        "salary": "99934",
        "id": "2466789",
        "city": "Монсон",
        "year": "2003",
        "age": "56"
    },
    {
        "_id": "65a71e13ef7de121883fbc9a",
        "job": "Психолог",
        "salary": "99934",
        "id": "2466789",
        "city": "Монсон",
        "year": "2003",
        "age": "56"
    },
    {
        "_id": "65a7963a699e1bc7fc5bc373",
        "job": "Психолог",
        "salary": "99934",
        "id": "2466789",
        "city": "Монсон",
        "year": "2003",
        "age": "56"
    },
    {
        "_id": "65a71ef3ef7de121883fbf66",
        "job": "Психолог",
        "salary": "99934",
        "id": "2466789",
        "city": "Монсон",
        "year": "2003",
        "age": "56"
    },
    {
        "_id": "65a72118ef7de121883fc4fe",
        "job": "Психолог",
        "salary": "99934",
        "id": "2466789",
        "city": "Монсон",
        "year": "2003",
        "age": "56"
    },
    {
        "_id": "65a72118ef7de121883fc4c7",
        "job": "Менеджер",
        "salary": "99910",
        "id": "9399458",
        "city": "Белград",
        "year": "2015",
        "age": "58"
    },
    {
        "_id": "65a7963a699e1bc7fc5bc33c",
        "job": "Менеджер",
        "salary": "99910",
        "id": "9399458",
        "city": "Белград",
        "year": "2015",
        "age": "58"
    },
    {
        "_id": "65a72102ef7de121883fc1fb",
        "job": "Менеджер",
        "salary": "99910",
        "id": "9399458",
        "city": "Белград",
        "year": "2015",
        "age": "58"
    },
    {
        "_id": "65a71ef3ef7de121883fbf2f",
        "job": "Менеджер",
        "salary": "99910",
        "id": "9399458",
        "city": "Белград",
        "year": "2015",
        "age": "58"
    },
    {
        "_id": "65a71e13ef7de121883fbc63",
        "job": "Менеджер",
        "salary": "99910",
        "id": "9399458",
        "city": "Белград",
        "year": "2015",
        "age": "58"
    }
]