[{"name": "delightful screws", "update_counter": 0}, {"name": "Logitech Wireless Keyboard", "update_counter": 0}, {"name": "amazing raspberry", "update_counter": 0}, {"name": "elegant hammer", "update_counter": 0}, {"name": "stylish paint", "update_counter": 0}, {"name": "SteelSeries Arctis 7", "update_counter": 0}, {"name": "tasteful kiwifruit", "update_counter": 0}, {"name": "Epson Expression Home XP", "update_counter": 0}, {"name": "Logitech Wireless Keyboard", "update_counter": 0}, {"name": "attractive drywall", "update_counter": 0}]